LICENSE
ecsmgmt/__init__.py
ecsmgmt/_util/__init__.py
ecsmgmt/_util/callbacks.py
ecsmgmt/_util/const.py
ecsmgmt/_util/core.py
ecsmgmt/_util/echo.py
ecsmgmt/_util/exceptions.py
ecsmgmt/_util/format.py
ecsmgmt/_util/types.py
ecsmgmt/bucket/__init__.py
ecsmgmt/bucket/acl/__init__.py
ecsmgmt/bucket/acl/get.py
ecsmgmt/bucket/acl/set.py
ecsmgmt/bucket/chown.py
ecsmgmt/bucket/create.py
ecsmgmt/bucket/delete.py
ecsmgmt/bucket/get.py
ecsmgmt/bucket/list.py
ecsmgmt/bucket/retention/__init__.py
ecsmgmt/bucket/retention/get.py
ecsmgmt/bucket/retention/set.py
ecsmgmt/get_acl_permissions.py
ecsmgmt/secret_key/__init__.py
ecsmgmt/secret_key/create.py
ecsmgmt/secret_key/delete.py
ecsmgmt/secret_key/list.py
ecsmgmt/user/__init__.py
ecsmgmt/user/create.py
ecsmgmt/user/delete.py
ecsmgmt/user/get.py
ecsmgmt/user/list.py
ecsmgmt_cli-0.6.0.dist-info/LICENSE
ecsmgmt_cli-0.6.0.dist-info/METADATA
ecsmgmt_cli-0.6.0.dist-info/WHEEL
ecsmgmt_cli-0.6.0.dist-info/entry_points.txt
ecsmgmt_cli-0.6.0.dist-info/RECORD
